{
  "id": "toilet",
  "name": "Toilet",
  "category": "entity",
  "base": "base_furniture",
  "components": {
    "sprite": {
      "source": "sprite.png",
      "srcX": 0,
      "srcY": 0,
      "width": 32,
      "height": 32,
      "layerDepth": 0.5
    },
    "collider": {
      "width": 24,
      "height": 24,
      "offsetX": -12,
      "offsetY": -12
    },
    "info": {
      "description": "Отхожее место. Простое, но необходимое удобство."
    },
    "interactable": {
      "name": "Toilet",
      "range": 72
    },
    "toilet": {}
  }
}
